prediction_prophet/__init__.py
prediction_prophet/app.py
prediction_prophet/autonolas/__init__.py
prediction_prophet/autonolas/research.py
prediction_prophet/benchmark/__init__.py
prediction_prophet/benchmark/agents.py
prediction_prophet/bot.py
prediction_prophet/functions/__init__.py
prediction_prophet/functions/cache.py
prediction_prophet/functions/create_embeddings_from_results.py
prediction_prophet/functions/debate_prediction.py
prediction_prophet/functions/evaluate_question.py
prediction_prophet/functions/generate_subqueries.py
prediction_prophet/functions/is_predictable_and_binary.py
prediction_prophet/functions/parallelism.py
prediction_prophet/functions/prepare_report.py
prediction_prophet/functions/rephrase_question.py
prediction_prophet/functions/rerank_results.py
prediction_prophet/functions/rerank_subqueries.py
prediction_prophet/functions/research.py
prediction_prophet/functions/scrape_results.py
prediction_prophet/functions/search.py
prediction_prophet/functions/summarize.py
prediction_prophet/functions/utils.py
prediction_prophet/functions/web_scrape.py
prediction_prophet/functions/web_search.py
prediction_prophet/main.py
prediction_prophet/models/WebScrapeResult.py
prediction_prophet/models/WebSearchResult.py
prediction_prophet-0.1.11.dist-info/LICENSE
prediction_prophet-0.1.11.dist-info/METADATA
prediction_prophet-0.1.11.dist-info/WHEEL
prediction_prophet-0.1.11.dist-info/entry_points.txt
prediction_prophet-0.1.11.dist-info/RECORD
