Metadata-Version: 2.1
Name: prediction-prophet
Version: 0.1.11
Summary: 
Author: Nestor Amesty
Author-email: nestor@polywrap.io
Requires-Python: >=3.10,<3.11
Classifier: Programming Language :: Python :: 3
Classifier: Programming Language :: Python :: 3.10
Requires-Dist: beautifulsoup4 (>=4.12.3,<5.0.0)
Requires-Dist: chromadb (==0.4.22)
Requires-Dist: click (>=8.0.2,<9.0.0)
Requires-Dist: discord (>=2.3.2,<3.0.0)
Requires-Dist: google-api-python-client (==2.95.0)
Requires-Dist: joblib (>=1.3.2,<2.0.0)
Requires-Dist: langchain (>=0.1.9,<0.2.0)
Requires-Dist: langchain-community (>=0.0.32,<0.0.33)
Requires-Dist: langchain-openai (>=0.0.5,<0.0.6)
Requires-Dist: markdownify (==0.11.6)
Requires-Dist: matplotlib (>=3.8.3,<4.0.0)
Requires-Dist: memory-profiler (>=0.61.0,<0.62.0)
Requires-Dist: openai (>=1.10.0,<2.0.0)
Requires-Dist: pandas (==2.1.1)
Requires-Dist: prediction-market-agent-tooling[google,langchain] (>=0.13.1,<0.14.0)
Requires-Dist: pyautogen (>=0.2.19,<0.3.0)
Requires-Dist: pysqlite3-binary (>=0.5.2.post3,<0.6.0) ; sys_platform == "linux"
Requires-Dist: pytest (>=8.0.0,<9.0.0)
Requires-Dist: scikit-learn (>=1.4.0,<2.0.0)
Requires-Dist: scipy (>=1.12.0,<2.0.0)
Requires-Dist: spacy (==3.7.2)
Requires-Dist: streamlit (>=1.30.0,<2.0.0)
Requires-Dist: tabulate (>=0.9.0,<0.10.0)
Requires-Dist: tavily-python (>=0.3.0,<0.4.0)
Requires-Dist: tenacity (>=8.2.3,<9.0.0)
Requires-Dist: tiktoken (==0.5.2)
Requires-Dist: typer (>=0.9.0,<0.10.0)
Requires-Dist: types-python-dateutil (>=2.8.19.20240106,<3.0.0.0)
Requires-Dist: types-requests (>=2.31.0.20240125,<3.0.0.0)
Requires-Dist: watchdog (>=3.0.0,<4.0.0)
